rusttypes/__init__.py
rusttypes/misc.py
rusttypes/option.py
rusttypes/result.py
rusttypes/traits.py
rusttypes-0.1.0.dist-info/LICENSE
rusttypes-0.1.0.dist-info/METADATA
rusttypes-0.1.0.dist-info/WHEEL
rusttypes-0.1.0.dist-info/RECORD
