Metadata-Version: 2.1
Name: rusttypes
Version: 0.1.0
Summary: Extra Datatypes for Python 3
Home-page: https://hendrikboeck.github.io/rusttypes-p3
License: BSD-3-Clause
Keywords: rusttypes,rust,result,option,types,python,datastructures,datatypes,collections
Author: Hendrik Boeck
Author-email: hendrikboeck.dev@protonmail.com
Requires-Python: >=3.11,<4.0
Classifier: Intended Audience :: Developers
Classifier: License :: OSI Approved :: BSD License
Classifier: Operating System :: OS Independent
Classifier: Programming Language :: Python :: 3
Classifier: Programming Language :: Python :: 3.11
Classifier: Programming Language :: Python :: 3.12
Classifier: Topic :: Software Development :: Libraries
Classifier: Topic :: Software Development :: Libraries :: Python Modules
Classifier: Typing :: Typed
Project-URL: Documentation, https://hendrikboeck.github.io/rusttypes-py3
Project-URL: Repository, https://github.com/hendrikboeck/rusttypes-py3
